Metadata-Version: 2.1
Name: ClusterConfig
Version: 20231230
Summary: Highly Available key value store for atomic updates - Replicated and Strongly Consistent
Home-page: https://github.com/magicray/ClusterConfig
Author: Bhupendra Singh
Author-email: bhsingh@gmail.com
Keywords: paxos,consistent,replicated,cluster,config
License-File: LICENSE
